si_prefix/LICENSE.md
si_prefix/README.md
si_prefix/__init__.py
videojitter/_signal.py
videojitter/_util.py
videojitter/_version.py
videojitter/_version_generated.py
videojitter/analyze_recording.py
videojitter/generate_fake_recording.py
videojitter/generate_report.py
videojitter/generate_spec.py
videojitter/generate_video.py
videojitter-1.0.1.dist-info/LICENSE.txt
videojitter-1.0.1.dist-info/METADATA
videojitter-1.0.1.dist-info/WHEEL
videojitter-1.0.1.dist-info/entry_points.txt
videojitter-1.0.1.dist-info/top_level.txt
videojitter-1.0.1.dist-info/RECORD
